{"results":[{"id":"03433","text":"Thị trấn Mường Tè"},{"id":"03436","text":"Xã Thu Lũm"},{"id":"03439","text":"Xã Ka Lăng"},{"id":"03440","text":"Xã Tá Bạ"},{"id":"03442","text":"Xã Pa ủ"},{"id":"03445","text":"Xã Mường Tè"},{"id":"03448","text":"Xã Pa Vệ Sử"},{"id":"03451","text":"Xã Mù Cả"},{"id":"03454","text":"Xã Bun Tở"},{"id":"03457","text":"Xã Nậm Khao"},{"id":"03463","text":"Xã Tà Tổng"},{"id":"03466","text":"Xã Bun Nưa"},{"id":"03467","text":"Xã Vàng San"},{"id":"03469","text":"Xã Kan Hồ"}],"pagination":{"more":false}}