{"results":[{"id":"08053","text":"Thị trấn Hạ Hoà"},{"id":"08056","text":"Xã Đại Phạm"},{"id":"08059","text":"Xã Hậu Bổng"},{"id":"08062","text":"Xã Đan Hà"},{"id":"08065","text":"Xã Hà Lương"},{"id":"08068","text":"Xã Lệnh Khanh"},{"id":"08071","text":"Xã Phụ Khánh"},{"id":"08074","text":"Xã Liên Phương"},{"id":"08077","text":"Xã Đan Thượng"},{"id":"08080","text":"Xã Hiền Lương"},{"id":"08083","text":"Xã Động Lâm"},{"id":"08086","text":"Xã Lâm Lợi"},{"id":"08089","text":"Xã Phương Viên"},{"id":"08092","text":"Xã Gia Điền"},{"id":"08095","text":"Xã Ấm Hạ"},{"id":"08098","text":"Xã Quân Khê"},{"id":"08101","text":"Xã Y Sơn"},{"id":"08104","text":"Xã Hương Xạ"},{"id":"08107","text":"Xã Cáo Điền"},{"id":"08110","text":"Xã Xuân Áng"},{"id":"08113","text":"Xã Yên Kỳ"},{"id":"08116","text":"Xã Chuế Lưu"},{"id":"08119","text":"Xã Minh Hạc"},{"id":"08122","text":"Xã Lang Sơn"},{"id":"08125","text":"Xã Bằng Giã"},{"id":"08128","text":"Xã Yên Luật"},{"id":"08131","text":"Xã Vô Tranh"},{"id":"08134","text":"Xã Văn Lang"},{"id":"08137","text":"Xã Chính Công"},{"id":"08140","text":"Xã Minh Côi"},{"id":"08143","text":"Xã Vĩnh Chân"},{"id":"08146","text":"Xã Mai Tùng"},{"id":"08149","text":"Xã Vụ Cầu"}],"pagination":{"more":false}}