{"results":[{"id":"11824","text":"Thị trấn Vĩnh Bảo"},{"id":"11827","text":"Xã Dũng Tiến"},{"id":"11830","text":"Xã Giang Biên"},{"id":"11833","text":"Xã Thắng Thuỷ"},{"id":"11836","text":"Xã Trung Lập"},{"id":"11839","text":"Xã Việt Tiến"},{"id":"11842","text":"Xã Vĩnh An"},{"id":"11845","text":"Xã Vĩnh Long"},{"id":"11848","text":"Xã Hiệp Hoà"},{"id":"11851","text":"Xã Hùng Tiến"},{"id":"11854","text":"Xã An Hoà"},{"id":"11857","text":"Xã Tân Hưng"},{"id":"11860","text":"Xã Tân Liên"},{"id":"11863","text":"Xã Nhân Hoà"},{"id":"11866","text":"Xã Tam Đa"},{"id":"11869","text":"Xã Hưng Nhân"},{"id":"11872","text":"Xã Vinh Quang"},{"id":"11875","text":"Xã Đồng Minh"},{"id":"11878","text":"Xã Thanh Lương"},{"id":"11881","text":"Xã Liên Am"},{"id":"11884","text":"Xã Lý Học"},{"id":"11887","text":"Xã Tam Cường"},{"id":"11890","text":"Xã Hoà Bình"},{"id":"11893","text":"Xã Tiền Phong"},{"id":"11896","text":"Xã Vĩnh Phong"},{"id":"11899","text":"Xã Cộng Hiền"},{"id":"11902","text":"Xã Cao Minh"},{"id":"11905","text":"Xã Cổ Am"},{"id":"11908","text":"Xã Vĩnh Tiến"},{"id":"11911","text":"Xã Trấn Dương"}],"pagination":{"more":false}}