{"results":[{"id":"23281","text":"Phường Quang Trung"},{"id":"23284","text":"Phường Duy Tân"},{"id":"23287","text":"Phường Quyết Thắng"},{"id":"23290","text":"Phường Trường Chinh"},{"id":"23293","text":"Phường Thắng Lợi"},{"id":"23296","text":"Phường Ngô Mây"},{"id":"23299","text":"Phường Thống Nhất"},{"id":"23302","text":"Phường Lê Lợi"},{"id":"23305","text":"Phường Nguyễn Trãi"},{"id":"23308","text":"Phường Trần Hưng Đạo"},{"id":"23311","text":"Xã Đắk Cấm"},{"id":"23314","text":"Xã Kroong"},{"id":"23317","text":"Xã Ngọk Bay"},{"id":"23320","text":"Xã Vinh Quang"},{"id":"23323","text":"Xã Đắk Blà"},{"id":"23326","text":"Xã Ia Chim"},{"id":"23327","text":"Xã Đăk Năng"},{"id":"23329","text":"Xã Đoàn Kết"},{"id":"23332","text":"Xã Chư Hreng"},{"id":"23335","text":"Xã Đắk Rơ Wa"},{"id":"23338","text":"Xã Hòa Bình"}],"pagination":{"more":false}}