{"results":[{"id":"24868","text":"Thị trấn Nam Ban"},{"id":"24871","text":"Thị trấn Đinh Văn"},{"id":"24880","text":"Xã Phú Sơn"},{"id":"24883","text":"Xã Phi Tô"},{"id":"24892","text":"Xã Mê Linh"},{"id":"24895","text":"Xã Đạ Đờn"},{"id":"24898","text":"Xã Phúc Thọ"},{"id":"24901","text":"Xã Đông Thanh"},{"id":"24904","text":"Xã Gia Lâm"},{"id":"24907","text":"Xã Tân Thanh"},{"id":"24910","text":"Xã Tân Văn"},{"id":"24913","text":"Xã Hoài Đức"},{"id":"24916","text":"Xã Tân Hà"},{"id":"24919","text":"Xã Liên Hà"},{"id":"24922","text":"Xã Đan Phượng"},{"id":"24925","text":"Xã Nam Hà"}],"pagination":{"more":false}}