{"results":[{"id":"25993","text":"Phường Trảng Dài"},{"id":"25996","text":"Phường Tân Phong"},{"id":"25999","text":"Phường Tân Biên"},{"id":"26002","text":"Phường Hố Nai"},{"id":"26005","text":"Phường Tân Hòa"},{"id":"26008","text":"Phường Tân Hiệp"},{"id":"26011","text":"Phường Bửu Long"},{"id":"26014","text":"Phường Tân Tiến"},{"id":"26017","text":"Phường Tam Hiệp"},{"id":"26020","text":"Phường Long Bình"},{"id":"26023","text":"Phường Quang Vinh"},{"id":"26026","text":"Phường Tân Mai"},{"id":"26029","text":"Phường Thống Nhất"},{"id":"26032","text":"Phường Trung Dũng"},{"id":"26035","text":"Phường Tam Hòa"},{"id":"26038","text":"Phường Hòa Bình"},{"id":"26041","text":"Phường Quyết Thắng"},{"id":"26044","text":"Phường Thanh Bình"},{"id":"26047","text":"Phường Bình Đa"},{"id":"26050","text":"Phường An Bình"},{"id":"26053","text":"Phường Bửu Hòa"},{"id":"26056","text":"Phường Long Bình Tân"},{"id":"26059","text":"Phường Tân Vạn"},{"id":"26062","text":"Xã Tân Hạnh"},{"id":"26065","text":"Xã Hiệp Hòa"},{"id":"26068","text":"Xã Hóa An"},{"id":"26371","text":"Xã An Hoà"},{"id":"26374","text":"Xã Tam Phước"},{"id":"26377","text":"Xã Phước Tân"},{"id":"26380","text":"Xã Long Hưng"}],"pagination":{"more":false}}