{"results":[{"id":"28159","text":"Thị trấn Cần Giuộc"},{"id":"28162","text":"Xã Phước Lý"},{"id":"28165","text":"Xã Long Thượng"},{"id":"28168","text":"Xã Long Hậu"},{"id":"28171","text":"Xã Tân Kim"},{"id":"28174","text":"Xã Phước Hậu"},{"id":"28177","text":"Xã Mỹ Lộc"},{"id":"28180","text":"Xã Phước Lại"},{"id":"28183","text":"Xã Phước Lâm"},{"id":"28186","text":"Xã Trường Bình"},{"id":"28189","text":"Xã Thuận Thành"},{"id":"28192","text":"Xã Phước Vĩnh Tây"},{"id":"28195","text":"Xã Phước Vĩnh Đông"},{"id":"28198","text":"Xã Long An"},{"id":"28201","text":"Xã Long Phụng"},{"id":"28204","text":"Xã Đông Thạnh"},{"id":"28207","text":"Xã Tân Tập"}],"pagination":{"more":false}}